oceanAlgorithmPrivate/__init__.py
oceanAlgorithmPrivate/common.py
oceanAlgorithmPrivate-0.0.48.dist-info/METADATA
oceanAlgorithmPrivate-0.0.48.dist-info/WHEEL
oceanAlgorithmPrivate-0.0.48.dist-info/top_level.txt
oceanAlgorithmPrivate-0.0.48.dist-info/RECORD
