Metadata-Version: 2.1
Name: oceanAlgorithmPrivate
Version: 0.0.48
Summary: PYPI ocean Algorithm private file written by Terry
Home-page: https://www.linkedin.com/in/tae-ung-hwang-790014221/
Author: taeung28
Author-email: taeung28@gmail.com
License: UNKNOWN
Keywords: terry,oceanAi,algorithm,private,pypi
Platform: UNKNOWN
Classifier: Programming Language :: Python :: 3.6
Classifier: Programming Language :: Python :: 3.7
Classifier: Programming Language :: Python :: 3.8
Classifier: Programming Language :: Python :: 3.9
Requires-Python: >=3.6
Requires-Dist: boto3 (==1.36.00)
Requires-Dist: botocore (==1.36.00)
Requires-Dist: contourpy (==1.1.1)
Requires-Dist: cycler (==0.12.1)
Requires-Dist: fonttools (==4.53.0)
Requires-Dist: importlib-resources (==6.4.0)
Requires-Dist: jmespath (==1.0.1)
Requires-Dist: joblib (==1.4.2)
Requires-Dist: kiwisolver (==1.4.5)
Requires-Dist: logtos3 (==0.0.19)
Requires-Dist: matplotlib (==3.7.5)
Requires-Dist: numpy (==1.24.4)
Requires-Dist: packaging (==24.1)
Requires-Dist: pandas (==2.0.3)
Requires-Dist: patsy (==0.5.6)
Requires-Dist: pillow (==10.3.0)
Requires-Dist: pyparsing (==3.1.2)
Requires-Dist: python-dateutil (==2.9.0.post0)
Requires-Dist: pytz (==2024.1)
Requires-Dist: s3transfer (==0.11.0)
Requires-Dist: scikit-learn (==1.3.2)
Requires-Dist: six (==1.16.0)
Requires-Dist: statsmodels (==0.14.1)
Requires-Dist: threadpoolctl (==3.5.0)
Requires-Dist: tzdata (==2024.1)
Requires-Dist: urllib3 (==1.26.20)
Requires-Dist: zipp (==3.19.2)
